feynmagi/CronManager.py
feynmagi/Job.py
feynmagi/__init__.py
feynmagi/agentdev.py
feynmagi/agents.py
feynmagi/audio.py
feynmagi/autollm.py
feynmagi/commands.py
feynmagi/config.py
feynmagi/digest.py
feynmagi/feynmagi.py
feynmagi/helper.py
feynmagi/interpreter.py
feynmagi/llmsapis.py
feynmagi/logger.py
feynmagi/mailing.py
feynmagi/mcts.py
feynmagi/playAgent.py
feynmagi/scheduler.py
feynmagi/sessions.py
feynmagi/socketio_instance.py
feynmagi/tasks-Copy1.py
feynmagi/tasks.py
feynmagi/tools.py
feynmagi/vectorsdb.py
feynmagi/videoops.py
feynmagi/websearch.py
feynmagi/data/agents.json
feynmagi/data/config_mail_to_do.json
feynmagi/data/mylog.log
feynmagi/data/.ipynb_checkpoints/config-checkpoint.txt
feynmagi/data/ragmem4_dir/0.txt
feynmagi/data/ragmem4_dir/1.txt
feynmagi/data/ragmem4_dir/2.txt
feynmagi/data/ragmem4_dir/3.txt
feynmagi/data/ragmem4_dir/4.txt
feynmagi/data/ragmem4_dir/ragmem.pkl
feynmagi/data/sessions_history/20240923084037.json
feynmagi/data/working/email.txt
feynmagi/data/working/email_content.txt
feynmagi/data/working/email_summary.txt
feynmagi/data/working/error.log
feynmagi/data/working/summary.txt
feynmagi/data/working/visited_papers.txt
feynmagi/data/working/visited_papers_llms.txt
feynmagi/data/working/vizited_papers_llms.txt
feynmagi/data/working/http___arxiv_org_pdf_2308_11432/0.txt
feynmagi/data/working/http___arxiv_org_pdf_2308_11432/1.txt
feynmagi/data/working/http___arxiv_org_pdf_2308_11432/10.txt
feynmagi/data/working/http___arxiv_org_pdf_2308_11432/11.txt
feynmagi/data/working/http___arxiv_org_pdf_2308_11432/12.txt
feynmagi/data/working/http___arxiv_org_pdf_2308_11432/13.txt
feynmagi/data/working/http___arxiv_org_pdf_2308_11432/14.txt
feynmagi/data/working/http___arxiv_org_pdf_2308_11432/15.txt
feynmagi/data/working/http___arxiv_org_pdf_2308_11432/16.txt
feynmagi/data/working/http___arxiv_org_pdf_2308_11432/17.txt
feynmagi/data/working/http___arxiv_org_pdf_2308_11432/18.txt
feynmagi/data/working/http___arxiv_org_pdf_2308_11432/19.txt
feynmagi-0.1.31.dist-info/METADATA
feynmagi-0.1.31.dist-info/WHEEL
feynmagi-0.1.31.dist-info/entry_points.txt
feynmagi-0.1.31.dist-info/top_level.txt
feynmagi-0.1.31.dist-info/RECORD
