Metadata-Version: 2.1
Name: feynmagi
Version: 0.1.31
Summary: Feynmagi is a multi-modal LLM interactive agents solution.
Home-page: https://github.com/Imag2020/feynmagi
Author: Imed MAGROUNE
Author-email: imed@magroune.net
License: UNKNOWN
Platform: UNKNOWN
Classifier: Programming Language :: Python :: 3
Classifier: License :: OSI Approved :: MIT License
Classifier: Operating System :: OS Independent
Requires-Python: >=3.6
Requires-Dist: Flask (==3.0.3)
Requires-Dist: Flask-SocketIO (==5.3.6)
Requires-Dist: Jinja2 (==3.1.2)
Requires-Dist: Pillow (==10.3.0)
Requires-Dist: Requests (==2.32.3)
Requires-Dist: apscheduler (==3.10.4)
Requires-Dist: beautifulsoup4 (==4.12.3)
Requires-Dist: charset-normalizer (==3.3.0)
Requires-Dist: cryptography (==41.0.1)
Requires-Dist: docker-py (==1.10.6)
Requires-Dist: groq (==0.9.0)
Requires-Dist: ipython (==8.16.1)
Requires-Dist: librosa (==0.10.1)
Requires-Dist: numpy (==1.26.4)
Requires-Dist: openai (>=1.45)
Requires-Dist: opencv-python
Requires-Dist: orjson (==3.10.5)
Requires-Dist: pdfplumber (>=0.11.4)
Requires-Dist: pydub (==0.25.1)
Requires-Dist: regex (==2023.10.3)
Requires-Dist: selenium (==4.21.0)
Requires-Dist: soundfile (==0.12.1)
Requires-Dist: torch (>=2.1.0)
Requires-Dist: transformers (<5.0.0,>=4.41.0)
Requires-Dist: watchdog (>=3.0.0)
